{
 "options": [
  [
   "cairo:fontconfig",
   "True"
  ],
  [
   "cairo:introspection",
   "True"
  ],
  [
   "cairo:png",
   "True"
  ],
  [
   "cairo:zlib",
   "True"
  ],
  [
   "gstreamer:check",
   "True"
  ],
  [
   "gstreamer:introspection",
   "True"
  ],
  [
   "gstreamer:tools",
   "True"
  ],
  [
   "gstreamer-plugins-base:app",
   "True"
  ],
  [
   "gstreamer-plugins-base:audioconvert",
   "True"
  ],
  [
   "gstreamer-plugins-base:audioresample",
   "False"
  ],
  [
   "gstreamer-plugins-base:audiotestsrc",
   "True"
  ],
  [
   "gstreamer-plugins-base:gl",
   "True"
  ],
  [
   "gstreamer-plugins-base:introspection",
   "True"
  ],
  [
   "gstreamer-plugins-base:opus",
   "True"
  ],
  [
   "gstreamer-plugins-base:orc",
   "True"
  ],
  [
   "gstreamer-plugins-base:pango",
   "True"
  ],
  [
   "gstreamer-plugins-base:playback",
   "True"
  ],
  [
   "gstreamer-plugins-base:timeoverlay",
   "True"
  ],
  [
   "gstreamer-plugins-base:typefind",
   "True"
  ],
  [
   "gstreamer-plugins-base:videoconvert",
   "True"
  ],
  [
   "gstreamer-plugins-base:videoscale",
   "True"
  ],
  [
   "gstreamer-plugins-base:videotestsrc",
   "True"
  ],
  [
   "gstreamer-plugins-base:x11",
   "True"
  ]
 ],
 "root": {
  "name": "gst-rgbd",
  "version": "master",
  "user": "aivero",
  "channel": "stable"
 }
}